Metadata-Version: 2.1
Name: tensorboardX-hparams
Version: 1.7.2
Summary: TensorBoardX with hparams support
Home-page: https://github.com/eisenjulian/tensorboardX/tree/enable-gitless-install
Author: Julian Eisenschlos
Author-email: eisenjulian@gmail.com
License: MIT license
Platform: UNKNOWN
Classifier: Development Status :: 2 - Pre-Alpha
Classifier: Intended Audience :: Developers
Classifier: License :: OSI Approved :: MIT License
Classifier: Natural Language :: English
Classifier: Programming Language :: Python :: 2
Classifier: Programming Language :: Python :: 2.7
Classifier: Programming Language :: Python :: 3
Classifier: Programming Language :: Python :: 3.4
Classifier: Programming Language :: Python :: 3.5
Classifier: Programming Language :: Python :: 3.6
